aiohappyeyeball/__init__.py
aiohappyeyeball/_staggered.py
aiohappyeyeball/impl.py
aiohappyeyeball/types.py
aiohappyeyeball/utils.py
aiohappyeyeball/__pycache__/staggerd.pyc
aiohappyeyeball-2.6.1.dist-info/METADATA
aiohappyeyeball-2.6.1.dist-info/WHEEL
aiohappyeyeball-2.6.1.dist-info/top_level.txt
aiohappyeyeball-2.6.1.dist-info/RECORD
