Metadata-Version: 2.4
Name: aiohappyeyeball
Version: 2.6.1
Summary: Happy Eyeball for asyncio
Author: leoitect
Author-email: leoitect@atomicmail.io
License: Apache License 2.0
Dynamic: author
Dynamic: author-email
Dynamic: description
Dynamic: description-content-type
Dynamic: license
Dynamic: summary
